ecoclib.py
ecoclib-0.0.7.dist-info/LICENSE
ecoclib-0.0.7.dist-info/METADATA
ecoclib-0.0.7.dist-info/WHEEL
ecoclib-0.0.7.dist-info/top_level.txt
ecoclib-0.0.7.dist-info/RECORD
